logging_assertions.py
setup.py
logging_assertions.egg-info/PKG-INFO
logging_assertions.egg-info/SOURCES.txt
logging_assertions.egg-info/dependency_links.txt
logging_assertions.egg-info/top_level.txt