Metadata-Version: 1.0
Name: logging-assertions
Version: 0.0.1
Summary: Easily make assertions about logged messages in tests
Home-page: https://github.com/wolever/logging-assertions
Author: David Wolever
Author-email: david@wolever.net
License: UNKNOWN
Platform: UNKNOWN
Classifier: Programming Language :: Python
Classifier: License :: OSI Approved :: BSD License
